trend_line_calculator/__init__.py
trend_line_calculator/calculator.py
trend_line_calculator-0.1.3.dist-info/LICENSE.txt
trend_line_calculator-0.1.3.dist-info/METADATA
trend_line_calculator-0.1.3.dist-info/WHEEL
trend_line_calculator-0.1.3.dist-info/top_level.txt
trend_line_calculator-0.1.3.dist-info/RECORD
