Metadata-Version: 2.1
Name: trend-line-calculator
Version: 0.1.3
Summary: Trend line calculator (example Python package)
Author: Wojciech Peisert
Author-email: wojtekp@sauron.pl
License: LICENCE.txt
License-File: LICENSE.txt
Requires-Dist: numpy
